a2m.itertools-0.2.0-py2.7-nspkg.pth
a2m/itertools.py
a2m.itertools-0.2.0.dist-info/DESCRIPTION.rst
a2m.itertools-0.2.0.dist-info/METADATA
a2m.itertools-0.2.0.dist-info/RECORD
a2m.itertools-0.2.0.dist-info/WHEEL
a2m.itertools-0.2.0.dist-info/metadata.json
a2m.itertools-0.2.0.dist-info/namespace_packages.txt
a2m.itertools-0.2.0.dist-info/top_level.txt
